bixin/__init__.py
bixin/data/__init__.py
bixin/data/dict.pkl
bixin/data/dict.txt.big
bixin-0.0.3.dist-info/METADATA
bixin-0.0.3.dist-info/WHEEL
bixin-0.0.3.dist-info/top_level.txt
bixin-0.0.3.dist-info/RECORD
