Metadata-Version: 2.1
Name: bixin
Version: 0.0.3
Summary: UNKNOWN
Home-page: UNKNOWN
License: UNKNOWN
Platform: UNKNOWN
Requires-Dist: cppjieba-py
Provides-Extra: dev
Requires-Dist: prefixtree (>=0.2.5) ; extra == 'dev'
Requires-Dist: chardet (>=3.0.4) ; extra == 'dev'
Requires-Dist: opencc-python-reimplemented (>=0.1.3) ; extra == 'dev'
Provides-Extra: test
Requires-Dist: spec (>=1.4.1) ; extra == 'test'
Requires-Dist: nose (>=1.3.7) ; extra == 'test'
